type_enum_plugin/__init__.py
type_enum_plugin/core.py
type_enum_plugin-0.5.0.dist-info/METADATA
type_enum_plugin-0.5.0.dist-info/WHEEL
type_enum_plugin-0.5.0.dist-info/RECORD
